source/__init__.py
source/module_print.py
helloworld_yaroslav2131234-0.1.0.dist-info/METADATA
helloworld_yaroslav2131234-0.1.0.dist-info/WHEEL
helloworld_yaroslav2131234-0.1.0.dist-info/top_level.txt
helloworld_yaroslav2131234-0.1.0.dist-info/RECORD
