Metadata-Version: 2.1
Name: helloworld-yaroslav2131234
Version: 0.1.0
Summary: A example Python package
Home-page: UNKNOWN
Author: Yaroslav Yaroslav
License: UNKNOWN
Platform: UNKNOWN
Requires-Dist: numpy (<1.20.0)
